{
  "coord": {
    "lon": 13.3996,
    "lat": 52.5238
  },
  "weather": [
    {
      "id": 500,
      "main": "Rain",
      "description": "light rain",
      "icon": "10n"
    }
  ],
  "base": "stations",
  "main": {
    "temp": 14.63,
    "feels_like": 13.72,
    "temp_min": 13.41,
    "temp_max": 15.06,
    "pressure": 1008,
    "humidity": 60,
    "sea_level": 1008,
    "grnd_level": 1002
  },
  "visibility": 10000,
  "wind": {
    "speed": 4.12,
    "deg": 50
  },
  "rain": {
    "1h": 0.12
  },
  "clouds": {
    "all": 0
  },
  "dt": 1778445325,
  "sys": {
    "type": 2,
    "id": 2039371,
    "country": "DE",
    "sunrise": 1778383127,
    "sunset": 1778438813
  },
  "timezone": 7200,
  "id": 6545310,
  "name": "Mitte",
  "cod": 200
}