{
  "coord": {
    "lon": 13.405,
    "lat": 52.52
  },
  "weather": [
    {
      "id": 800,
      "main": "Clear",
      "description": "clear sky",
      "icon": "01d"
    }
  ],
  "base": "stations",
  "main": {
    "temp": 14.75,
    "feels_like": 13.09,
    "temp_min": 13.56,
    "temp_max": 15.55,
    "pressure": 1025,
    "humidity": 31,
    "sea_level": 1025,
    "grnd_level": 1019
  },
  "visibility": 10000,
  "wind": {
    "speed": 3.09,
    "deg": 330
  },
  "clouds": {
    "all": 0
  },
  "dt": 1777214747,
  "sys": {
    "type": 2,
    "id": 2009543,
    "country": "DE",
    "sunrise": 1777175116,
    "sunset": 1777227771
  },
  "timezone": 7200,
  "id": 6545310,
  "name": "Mitte",
  "cod": 200
}