{
  "coord": {
    "lon": 13.405,
    "lat": 52.52
  },
  "weather": [
    {
      "id": 804,
      "main": "Clouds",
      "description": "overcast clouds",
      "icon": "04n"
    }
  ],
  "base": "stations",
  "main": {
    "temp": 3.44,
    "feels_like": 3.44,
    "temp_min": 3.44,
    "temp_max": 3.44,
    "pressure": 1017,
    "humidity": 85,
    "sea_level": 1017,
    "grnd_level": 1011
  },
  "visibility": 10000,
  "wind": {
    "speed": 1.07,
    "deg": 208,
    "gust": 1.07
  },
  "clouds": {
    "all": 100
  },
  "dt": 1773118407,
  "sys": {
    "country": "DE",
    "sunrise": 1773120783,
    "sunset": 1773162036
  },
  "timezone": 3600,
  "id": 6545310,
  "name": "Mitte",
  "cod": 200
}