{
  "coord": {
    "lon": 13.405,
    "lat": 52.52
  },
  "weather": [
    {
      "id": 803,
      "main": "Clouds",
      "description": "broken clouds",
      "icon": "04n"
    }
  ],
  "base": "stations",
  "main": {
    "temp": 14.43,
    "feels_like": 14.15,
    "temp_min": 12.79,
    "temp_max": 15.48,
    "pressure": 1016,
    "humidity": 85,
    "sea_level": 1016,
    "grnd_level": 1010
  },
  "visibility": 10000,
  "wind": {
    "speed": 2.53,
    "deg": 296,
    "gust": 5.09
  },
  "clouds": {
    "all": 78
  },
  "dt": 1780184591,
  "sys": {
    "type": 2,
    "id": 2012272,
    "country": "DE",
    "sunrise": 1780195846,
    "sunset": 1780255059
  },
  "timezone": 7200,
  "id": 6545310,
  "name": "Mitte",
  "cod": 200
}