{
  "coord": {
    "lon": 13.405,
    "lat": 52.52
  },
  "weather": [
    {
      "id": 801,
      "main": "Clouds",
      "description": "few clouds",
      "icon": "02d"
    }
  ],
  "base": "stations",
  "main": {
    "temp": 20.06,
    "feels_like": 19.71,
    "temp_min": 19.36,
    "temp_max": 21.68,
    "pressure": 1026,
    "humidity": 61,
    "sea_level": 1026,
    "grnd_level": 1020
  },
  "visibility": 10000,
  "wind": {
    "speed": 6.26,
    "deg": 260,
    "gust": 6.71
  },
  "clouds": {
    "all": 20
  },
  "dt": 1779371458,
  "sys": {
    "type": 2,
    "id": 2011538,
    "country": "DE",
    "sunrise": 1779332519,
    "sunset": 1779390254
  },
  "timezone": 7200,
  "id": 6545310,
  "name": "Mitte",
  "cod": 200
}