{
  "coord": {
    "lon": 13.405,
    "lat": 52.52
  },
  "weather": [
    {
      "id": 800,
      "main": "Clear",
      "description": "clear sky",
      "icon": "01n"
    }
  ],
  "base": "stations",
  "main": {
    "temp": 10.31,
    "feels_like": 8.55,
    "temp_min": 8.01,
    "temp_max": 11.05,
    "pressure": 1031,
    "humidity": 44,
    "sea_level": 1031,
    "grnd_level": 1025
  },
  "visibility": 10000,
  "wind": {
    "speed": 2.57,
    "deg": 100
  },
  "clouds": {
    "all": 0
  },
  "dt": 1777489202,
  "sys": {
    "type": 2,
    "id": 2000002,
    "country": "DE",
    "sunrise": 1777433952,
    "sunset": 1777487285
  },
  "timezone": 7200,
  "id": 6545310,
  "name": "Mitte",
  "cod": 200
}