{
  "coord": {
    "lon": 13.4,
    "lat": 52.52
  },
  "weather": [
    {
      "id": 800,
      "main": "Clear",
      "description": "clear sky",
      "icon": "01d"
    }
  ],
  "base": "stations",
  "main": {
    "temp": 14.2,
    "feels_like": 12.59,
    "temp_min": 14.2,
    "temp_max": 14.2,
    "pressure": 1024,
    "humidity": 35,
    "sea_level": 1024,
    "grnd_level": 1018
  },
  "visibility": 10000,
  "wind": {
    "speed": 3.81,
    "deg": 52,
    "gust": 5.24
  },
  "clouds": {
    "all": 8
  },
  "dt": 1776776402,
  "sys": {
    "country": "DE",
    "sunrise": 1776743746,
    "sunset": 1776795248
  },
  "timezone": 7200,
  "id": 6545310,
  "name": "Mitte",
  "cod": 200
}