{
  "coord": {
    "lon": 13.4,
    "lat": 52.52
  },
  "weather": [
    {
      "id": 801,
      "main": "Clouds",
      "description": "few clouds",
      "icon": "02d"
    }
  ],
  "base": "stations",
  "main": {
    "temp": 8.91,
    "feels_like": 6.38,
    "temp_min": 7.91,
    "temp_max": 9.97,
    "pressure": 1021,
    "humidity": 56,
    "sea_level": 1021,
    "grnd_level": 1014
  },
  "visibility": 10000,
  "wind": {
    "speed": 4.63,
    "deg": 290
  },
  "clouds": {
    "all": 20
  },
  "dt": 1774620001,
  "sys": {
    "type": 2,
    "id": 2009543,
    "country": "DE",
    "sunrise": 1774587175,
    "sunset": 1774632632
  },
  "timezone": 3600,
  "id": 6545310,
  "name": "Mitte",
  "cod": 200
}